flask_formist/__init__.py
flask_formist-0.1.0.dist-info/LICENSE
flask_formist-0.1.0.dist-info/METADATA
flask_formist-0.1.0.dist-info/WHEEL
flask_formist-0.1.0.dist-info/RECORD
