Metadata-Version: 2.1
Name: Flask-Formist
Version: 0.1.0
Summary: Flask extension for working with WTForms
Author: Rafal Padkowski
Author-email: rafaelp@poczta.onet.pl
Requires-Python: >=3.10
Classifier: Programming Language :: Python :: 3
Classifier: Programming Language :: Python :: 3.10
Classifier: Programming Language :: Python :: 3.11
Classifier: Programming Language :: Python :: 3.12
Requires-Dist: flask (>=3.0.1)
Requires-Dist: wtforms (>=3.1.2)
